cellx/__init__.py
cellx/cell.py
cellx/cellx.py
cellx/fullparser.py
cellx/object.py
cellx/parser.py
cellx/util.py
cellx/monitor/__init__.py
cellx/monitor/color.py
cellx/monitor/enh-postscript.py
cellx/monitor/null.py
cellx/monitor/opengl.py
cellx/monitor/postscript.py
cellx/monitor/sdl.py
cellx/monitor/sdl_filter.py
cellx-1.14.data/scripts/cellx
cellx-1.14.dist-info/LICENSE
cellx-1.14.dist-info/METADATA
cellx-1.14.dist-info/WHEEL
cellx-1.14.dist-info/top_level.txt
cellx-1.14.dist-info/RECORD
