Metadata-Version: 2.1
Name: cellx
Version: 1.14
Summary: command-driven drawing/visualization/animation/presentation tool
Home-page: https://github.com/h-ohsaki/cellx
Author: Hiroyuki Ohsaki
Author-email: ohsaki@lsnl.jp
License: UNKNOWN
Platform: UNKNOWN
Classifier: Programming Language :: Python :: 3
Classifier: License :: OSI Approved :: GNU General Public License v3 (GPLv3)
Classifier: Operating System :: OS Independent
Requires-Dist: PyOpenGL
Requires-Dist: pygame
